pyNTM/__init__.py
pyNTM/circuit.py
pyNTM/demand.py
pyNTM/exceptions.py
pyNTM/flex_model.py
pyNTM/interface.py
pyNTM/master_model.py
pyNTM/node.py
pyNTM/performance_model.py
pyNTM/rsvp.py
pyNTM/srlg.py
pyNTM/utilities.py
pyNTM/weathermap.py
pyntm-4.0.1.dist-info/licenses/LICENSE
test/__init__.py
test/test_circuit.py
test/test_demand.py
test/test_demand_parallel_link_model.py
test/test_igp_ecmp_routing.py
test/test_igp_shortcuts.py
test/test_interface.py
test/test_interface_parallel_link_model.py
test/test_model.py
test/test_node.py
test/test_parallel_link_model.py
test/test_rsvp_3rd_lsp_two_paths.py
test/test_rsvp_3rd_lsp_two_paths_parallel_links.py
test/test_rsvp_4th_lsp_two_paths.py
test/test_rsvp_configured_setup_bw.py
test/test_rsvp_int_failure_traff_add.py
test/test_rsvp_manual_metric.py
test/test_rsvplsp_int_failure.py
test/test_rsvplsp_path_selection.py
test/test_rsvplsp_setup.py
test/test_srlg.py
test/test_srlg_parallel_link_model.py
test/test_traffic_eng_features.py
test/test_utilities.py
pyntm-4.0.1.dist-info/METADATA
pyntm-4.0.1.dist-info/WHEEL
pyntm-4.0.1.dist-info/top_level.txt
pyntm-4.0.1.dist-info/RECORD
