Metadata-Version: 2.4
Name: pyNTM
Version: 4.0.1
Summary: Network traffic modeler API written in Python 3
Home-page: https://github.com/tim-fiola/network_traffic_modeler_py3
Download-URL: https://github.com/tim-fiola/network_traffic_modeler_py3/tarball/4.0.1
Author: Tim Fiola
Author-email: timothy.fiola@gmail.com
Keywords: networking,layer3,failover,modeling,model,pyNTM
License-File: LICENSE
Requires-Dist: networkx==3.1
Requires-Dist: jinja2
Requires-Dist: dash
Requires-Dist: dash-cytoscape
Requires-Dist: sphinx-rtd-theme
Dynamic: author
Dynamic: author-email
Dynamic: description
Dynamic: description-content-type
Dynamic: download-url
Dynamic: home-page
Dynamic: keywords
Dynamic: license-file
Dynamic: requires-dist
Dynamic: summary
